{
  "about_us": "ABOUT US",
  "discover_pyrmaids": "Discover Pyrmaids",
  "mission": "Mission",
  "safety_measures": "Safety Measures",
  "quality_assurance": "Quality Assurance",
  "services": "Services",
  "products": "Products",
  "contact_us": "Contact Us",
  "about_pyramids_adhesives": "About Pyramids Adhesives",
  "home": "Home",
  "›": "›",
  "about": "About",
  "packaging": "Packaging",
  "our_mission": "Our Mission",
  "pyramids_adhesives_is_a_leading_manufacturer_of_hot_melt_and_upholstery_adhesives._we_are_dedicated_to_providing_our_customers_with_the_highest_quality_products_and_services._our_team_of_experts_is_committed_to_helping_you_find_the_right_adhesive_solution_for_your_specific_needs._whether_you_are_looking_for_a_standard_adhesive_or_a_custom_formulation,_we_have_the_knowledge_and_experience_to_meet_your_requirements._contact_us_today_to_learn_more_about_our_products_and_services.": "Pyramids Adhesives is a leading manufacturer of hot melt and Upholstery adhesives. We are dedicated to providing our customers with the highest quality products and services. Our team of experts is committed to helping you find the right adhesive solution for your specific needs. Whether you are looking for a standard adhesive or a custom formulation, we have the knowledge and experience to meet your requirements. Contact us today to learn more about our products and services.",
  "clients_served": "Clients Served",
  "projects_completed": "Projects Completed",
  "revenue": "Revenue",
  "get_in_touch": "Get in Touch",
  "useful_links": "Useful Links",
  "info@pyramidsadhesives.com": "info@pyramidsadhesives.com",
  "©_2025_pyrmaids,_all_rights_reserved.": "© 2025 Pyrmaids, all rights reserved."
}